[{"event_id":"562204267097","title":"Japan Africa BizMatch Forum 2024","url":"https://www.eventbrite.com/e/japan-africa-bizmatch-forum-2024-tickets-562204267097","shortener_url":null,"started_at":"2024-10-08T08:00:00.000+09:00","ended_at":"2024-10-08T16:00:00.000+09:00","limit_number":null,"address":"6 Chome-6-2 Nishishinjuku, Shinjuku City, Tokyo 160-0023, Japan, Shinjuku City, NB 160-0023","place":"Hilton Tokyo","lat":35.6927,"lon":139.691,"state":"active","id":null},{"event_id":"bare-bones-jam-24","title":"The Bare-Bones Jam","url":"https://itch.io/jam/bare-bones-jam-24","shortener_url":null,"started_at":"2024-10-01T13:00:00.000+09:00","ended_at":"2024-10-31T13:00:00.000+09:00","limit_number":null,"address":null,"place":"Online","lat":null,"lon":null,"state":"active","id":null},{"event_id":"scream-jam-2024","title":" SCREAM JAM 2024 ","url":"https://itch.io/jam/scream-jam-2024","shortener_url":"https://bit.ly/3u5rWup","started_at":"2024-10-17T06:00:00.000+09:00","ended_at":"2024-10-24T06:00:00.000+09:00","limit_number":null,"address":null,"place":"Online","lat":null,"lon":null,"state":"active","id":null},{"event_id":"yuri-game-jam-2024","title":"Yuri Game Jam 2024","url":"https://itch.io/jam/yuri-game-jam-2024","shortener_url":"https://bit.ly/3SHka2g","started_at":"2024-10-01T08:00:00.000+09:00","ended_at":"2024-12-02T09:00:00.000+09:00","limit_number":null,"address":null,"place":"Online","lat":null,"lon":null,"state":"active","id":null},{"event_id":"dying-year-vn-jam","title":"Dying Year - Visual Novel Jam","url":"https://itch.io/jam/dying-year-vn-jam","shortener_url":null,"started_at":"2024-10-01T13:00:00.000+09:00","ended_at":"2025-01-01T14:00:00.000+09:00","limit_number":null,"address":null,"place":"Online","lat":null,"lon":null,"state":"active","id":null},{"event_id":"static-camera-jam","title":"Static Camera Jam","url":"https://itch.io/jam/static-camera-jam","shortener_url":"https://bit.ly/49hOWoC","started_at":"2024-10-22T12:00:00.000+09:00","ended_at":"2024-10-29T12:00:00.000+09:00","limit_number":null,"address":null,"place":"Online","lat":null,"lon":null,"state":"active","id":null},{"event_id":"theana-game-jam-weeklyjam-31","title":"Theana Game Jam - WeeklyJam #31","url":"https://itch.io/jam/theana-game-jam-weeklyjam-31","shortener_url":"https://bit.ly/3JTzpkp","started_at":"2024-10-06T22:00:00.000+09:00","ended_at":"2024-10-13T22:00:00.000+09:00","limit_number":null,"address":null,"place":"Online","lat":null,"lon":null,"state":"active","id":null},{"event_id":"slow-burn-jam","title":"The Slow-Burn Horror Jam","url":"https://itch.io/jam/slow-burn-jam","shortener_url":null,"started_at":"2024-10-01T12:00:00.000+09:00","ended_at":"2024-10-08T12:00:00.000+09:00","limit_number":null,"address":null,"place":"Online","lat":null,"lon":null,"state":"active","id":null},{"event_id":"174599","title":"♪ MAMEHICO LIVE「珈琲と音楽を　池田拓真（ギター）×友田ジュン（ピアノ）×山下あすか（パーカッション）」","url":"https://mamehicoginza.doorkeeper.jp/events/174599","shortener_url":null,"started_at":"2024-10-06T12:00:00.000+09:00","ended_at":"2024-10-06T14:00:00.000+09:00","limit_number":null,"address":"東京都中央区銀座2-2-18 TH 銀座ビル10F","place":"MAMEHICO 銀座","lat":35.6748,"lon":139.766,"state":"active","id":null},{"event_id":"devs-that-jam-36hr-challenge-oct24","title":"Devs That Jam 36hr Challenge #7","url":"https://itch.io/jam/devs-that-jam-36hr-challenge-oct24","shortener_url":null,"started_at":"2024-10-26T19:00:00.000+09:00","ended_at":"2024-10-28T08:00:00.000+09:00","limit_number":null,"address":null,"place":"Online","lat":null,"lon":null,"state":"active","id":null}]