[{"event_id":"309773","title":"【ほっこり】温泉合宿 in 箱根【八回目】","url":"https://svrkcho.connpass.com/event/309773/","shortener_url":"https://bit.ly/49zhmeq","started_at":"2025-02-15T13:00:00.000+09:00","ended_at":"2025-02-16T10:00:00.000+09:00","limit_number":96,"address":"神奈川県足柄下郡箱根町木賀1014","place":"KKR宮ノ下","lat":35.2455,"lon":139.055,"state":"active","id":null},{"event_id":"cyberpunk-game-jam-2","title":"Cyberpunk Game Jam 2.0","url":"https://itch.io/jam/cyberpunk-game-jam-2","shortener_url":"https://tiny.cc/m8pfzz","started_at":"2025-02-15T14:00:00.000+09:00","ended_at":"2025-02-25T13:59:59.000+09:00","limit_number":null,"address":null,"place":"Online","lat":null,"lon":null,"state":"active","id":null},{"event_id":"dps-horror-jam-2024","title":"Dark Poet Sonata Horror Game Jam 2025 ","url":"https://itch.io/jam/dps-horror-jam-2024","shortener_url":"https://tiny.cc/u02kzz","started_at":"2025-02-02T14:00:13.000+09:00","ended_at":"2025-03-03T02:00:13.000+09:00","limit_number":null,"address":null,"place":"Online","lat":null,"lon":null,"state":"active","id":null},{"event_id":"oprwj12","title":"OPR Writing Jam #12","url":"https://itch.io/jam/oprwj12","shortener_url":null,"started_at":"2025-02-08T05:00:00.000+09:00","ended_at":"2025-02-10T05:00:00.000+09:00","limit_number":null,"address":null,"place":"Online","lat":null,"lon":null,"state":"active","id":null},{"event_id":"zen-jam-10","title":"ZEN JAM #10","url":"https://itch.io/jam/zen-jam-10","shortener_url":null,"started_at":"2025-02-02T08:30:00.000+09:00","ended_at":"2025-02-16T08:30:00.000+09:00","limit_number":null,"address":null,"place":"Online","lat":null,"lon":null,"state":"active","id":null},{"event_id":"historically-accurate-game-jam-10","title":"Historically Accurate Game Jam 10","url":"https://itch.io/jam/historically-accurate-game-jam-10","shortener_url":"https://tiny.cc/dccrzz","started_at":"2025-02-22T00:00:00.000+09:00","ended_at":"2025-03-03T00:00:00.000+09:00","limit_number":null,"address":null,"place":"Online","lat":null,"lon":null,"state":"active","id":null},{"event_id":"pygame-jam-2025","title":" Pygame Jam 2025 - Cash Prizes","url":"https://itch.io/jam/pygame-jam-2025","shortener_url":"https://tiny.cc/cccrzz","started_at":"2025-02-08T18:00:00.000+09:00","ended_at":"2025-02-16T08:59:59.000+09:00","limit_number":null,"address":null,"place":"Online","lat":null,"lon":null,"state":"active","id":null},{"event_id":"178983","title":"［第9回］Startup Weekend 豊橋","url":"https://swtoyohashi.doorkeeper.jp/events/178983","shortener_url":null,"started_at":"2025-02-28T18:00:00.000+09:00","ended_at":"2025-03-02T19:00:00.000+09:00","limit_number":100,"address":"〒440-0888 愛知県豊橋市駅前大通１丁目１３５ 3F","place":"MUSASHi Innovation Lab CLUE","lat":34.7622,"lon":137.383,"state":"active","id":null},{"event_id":"335410","title":"実際の病院を会場にしたハッカソン！第4回メディカルハッカソン  by ものづくり医療センター","url":"https://moicen-forest.connpass.com/event/335410/","shortener_url":"https://tiny.cc/x5etzz","started_at":"2025-02-23T10:00:00.000+09:00","ended_at":"2025-02-24T18:00:00.000+09:00","limit_number":75,"address":"東京都足立区足立1-12-12","place":"足立慶友整形外科","lat":35.7642,"lon":139.804,"state":"active","id":null},{"event_id":"336013","title":"MLSE冬合宿2025","url":"https://mlxse.connpass.com/event/336013/","shortener_url":"https://tiny.cc/w5etzz","started_at":"2025-02-06T13:00:00.000+09:00","ended_at":"2025-02-08T12:30:00.000+09:00","limit_number":30,"address":"〒250-0408 神奈川県足柄下郡箱根町強羅1320-375","place":"箱根・強羅温泉 太陽山荘","lat":35.2506,"lon":139.046,"state":"active","id":null},{"event_id":"farm-jam-2025","title":"Farm Jam 2025 (Theme is voted on!)","url":"https://itch.io/jam/farm-jam-2025","shortener_url":null,"started_at":"2025-02-01T13:00:00.000+09:00","ended_at":"2025-03-03T13:00:00.000+09:00","limit_number":null,"address":null,"place":"Online","lat":null,"lon":null,"state":"active","id":null},{"event_id":"brackeys-13","title":"Brackeys Game Jam 2025.1","url":"https://itch.io/jam/brackeys-13","shortener_url":"https://tiny.cc/mqjtzz","started_at":"2025-02-16T20:00:00.000+09:00","ended_at":"2025-02-23T20:00:00.000+09:00","limit_number":null,"address":null,"place":"Online","lat":null,"lon":null,"state":"active","id":null},{"event_id":"impressions-composing-jam-ost-2","title":"Impressions Composing Jam: OST #2","url":"https://itch.io/jam/impressions-composing-jam-ost-2","shortener_url":null,"started_at":"2025-02-15T10:00:00.000+09:00","ended_at":"2025-03-03T11:00:00.000+09:00","limit_number":null,"address":null,"place":"Online","lat":null,"lon":null,"state":"active","id":null},{"event_id":"178394","title":"Startup Weekend Tsukuba 13th","url":"https://swtsukuba.doorkeeper.jp/events/178394","shortener_url":null,"started_at":"2025-02-28T18:00:00.000+09:00","ended_at":"2025-03-02T21:00:00.000+09:00","limit_number":50,"address":" co-en（つくば駅A3出口から徒歩3分）   茨城県つくば市吾妻1-10-1 つくばセンタービル1F","place":"co-en","lat":36.0813,"lon":140.114,"state":"active","id":null},{"event_id":"games-for-blind-gamers-4","title":"Games for Blind Gamers 4","url":"https://itch.io/jam/games-for-blind-gamers-4","shortener_url":null,"started_at":"2025-02-01T14:00:00.000+09:00","ended_at":"2025-03-01T13:59:59.000+09:00","limit_number":null,"address":null,"place":"Online","lat":null,"lon":null,"state":"active","id":null},{"event_id":"zzgj2025","title":"ZZGJ-PRE 2025","url":"https://itch.io/jam/zzgj2025","shortener_url":null,"started_at":"2025-02-01T01:00:00.000+09:00","ended_at":"2025-02-15T00:59:59.000+09:00","limit_number":null,"address":null,"place":"Online","lat":null,"lon":null,"state":"active","id":null},{"event_id":"cause-jam-31","title":"Cause Jam 31","url":"https://itch.io/jam/cause-jam-31","shortener_url":null,"started_at":"2025-02-08T10:00:00.000+09:00","ended_at":"2025-03-01T13:59:59.000+09:00","limit_number":null,"address":null,"place":"Online","lat":null,"lon":null,"state":"active","id":null},{"event_id":null,"title":"SMathHacks 2025","url":"https://smathhacks-2025.devpost.com/","shortener_url":null,"started_at":"2025-02-08T09:00:00.000+09:00","ended_at":"2025-02-09T09:00:00.000+09:00","limit_number":null,"address":null,"place":"Online","lat":null,"lon":null,"state":"active","id":null},{"event_id":null,"title":"HackVortex Codestorm 5","url":"https://hackvortex-codestorm-5.devpost.com/","shortener_url":null,"started_at":"2025-02-08T09:00:00.000+09:00","ended_at":"2025-02-22T09:00:00.000+09:00","limit_number":null,"address":null,"place":"Online","lat":null,"lon":null,"state":"active","id":null},{"event_id":"goedware-game-jam-13","title":"GoedWare Game Jam #13 (+ prizes )","url":"https://itch.io/jam/goedware-game-jam-13","shortener_url":null,"started_at":"2025-02-28T19:00:00.000+09:00","ended_at":"2025-03-10T19:00:00.000+09:00","limit_number":null,"address":null,"place":"Online","lat":null,"lon":null,"state":"active","id":null},{"event_id":"tummy-jam-2025","title":"Tummy Jam","url":"https://itch.io/jam/tummy-jam-2025","shortener_url":null,"started_at":"2025-02-01T14:00:00.000+09:00","ended_at":"2025-04-01T13:00:00.000+09:00","limit_number":null,"address":null,"place":"Online","lat":null,"lon":null,"state":"active","id":null},{"event_id":"orlando-game-jam-2025","title":"Orlando Game Jam 2025","url":"https://itch.io/jam/orlando-game-jam-2025","shortener_url":null,"started_at":"2025-02-28T06:00:00.000+09:00","ended_at":"2025-03-03T03:00:00.000+09:00","limit_number":null,"address":null,"place":"Online","lat":null,"lon":null,"state":"active","id":null},{"event_id":"unofficial-otter-jam-2025","title":"Unofficial Otter Jam 2025","url":"https://itch.io/jam/unofficial-otter-jam-2025","shortener_url":null,"started_at":"2025-02-28T16:59:00.000+09:00","ended_at":"2025-03-08T16:59:00.000+09:00","limit_number":null,"address":null,"place":"Online","lat":null,"lon":null,"state":"active","id":null},{"event_id":"b3agz-jam-2025","title":"b3agz Jam 2025","url":"https://itch.io/jam/b3agz-jam-2025","shortener_url":null,"started_at":"2025-02-28T09:01:00.000+09:00","ended_at":"2025-03-08T08:59:00.000+09:00","limit_number":null,"address":null,"place":"Online","lat":null,"lon":null,"state":"active","id":null},{"event_id":"335097","title":"KC3Hack 2025","url":"https://nxtend.connpass.com/event/335097/","shortener_url":null,"started_at":"2025-02-24T10:00:00.000+09:00","ended_at":"2025-02-24T19:00:00.000+09:00","limit_number":100,"address":"〒600-8815 京都府京都市下京区中堂寺粟田町93","place":"京都リサーチパーク","lat":34.9949,"lon":135.739,"state":"active","id":null},{"event_id":"focs-jam-2025-1","title":"FOCS Jam 2025.1","url":"https://itch.io/jam/focs-jam-2025-1","shortener_url":null,"started_at":"2025-02-15T02:00:00.000+09:00","ended_at":"2025-02-17T02:00:00.000+09:00","limit_number":null,"address":null,"place":"Online","lat":null,"lon":null,"state":"active","id":null},{"event_id":"180121","title":"【学生起業家プレゼン】静岡版起業家発掘！TOMOLプロジェクト成果発表会","url":"https://founderscircle.doorkeeper.jp/events/180121","shortener_url":null,"started_at":"2025-02-15T13:00:00.000+09:00","ended_at":"2025-02-15T17:30:00.000+09:00","limit_number":80,"address":"静岡県静岡市葵区紺屋町17-1","place":"有限責任監査法人トーマツ 17階セミナールーム","lat":34.9725,"lon":138.387,"state":"active","id":null},{"event_id":"179838","title":"【学生起業家プレゼン】静岡版起業家発掘！TOMOLプロジェクト成果発表会","url":"https://swshizuoka.doorkeeper.jp/events/179838","shortener_url":null,"started_at":"2025-02-15T13:00:00.000+09:00","ended_at":"2025-02-15T17:30:00.000+09:00","limit_number":70,"address":"静岡県静岡市葵区紺屋町17-1","place":"有限責任監査法人トーマツ 17階セミナールーム","lat":34.9725,"lon":138.387,"state":"active","id":null},{"event_id":null,"title":"HackAttack","url":"https://hackattack-smecit25.devpost.com/","shortener_url":null,"started_at":"2025-02-14T09:00:00.000+09:00","ended_at":"2025-02-15T08:59:59.999+09:00","limit_number":null,"address":null,"place":"Online","lat":null,"lon":null,"state":"active","id":null},{"event_id":"1-bit-jam-5","title":"1-BIT JAM #5","url":"https://itch.io/jam/1-bit-jam-5","shortener_url":null,"started_at":"2025-02-02T00:00:00.000+09:00","ended_at":"2025-02-09T00:00:00.000+09:00","limit_number":null,"address":null,"place":"Online","lat":null,"lon":null,"state":"active","id":null},{"event_id":"amare-games-festival-2025","title":"Amare Games Festival 2025","url":"https://itch.io/jam/amare-games-festival-2025","shortener_url":null,"started_at":"2025-02-01T13:00:00.000+09:00","ended_at":"2025-03-15T13:00:00.000+09:00","limit_number":null,"address":null,"place":"Online","lat":null,"lon":null,"state":"active","id":null},{"event_id":"make-visual-novels-assets-jam","title":"Make Visual Novel Assets! Jam","url":"https://itch.io/jam/make-visual-novels-assets-jam","shortener_url":null,"started_at":"2025-02-02T02:12:36.000+09:00","ended_at":"2025-02-16T02:12:54.000+09:00","limit_number":null,"address":null,"place":"Online","lat":null,"lon":null,"state":"active","id":null},{"event_id":"avalanche-neuranode-game-jam","title":"Avalanche | NeuraNode Game Jam - $19k in cash prizes!","url":"https://itch.io/jam/avalanche-neuranode-game-jam","shortener_url":null,"started_at":"2025-02-03T19:00:00.000+09:00","ended_at":"2025-03-04T07:00:00.000+09:00","limit_number":null,"address":null,"place":"Online","lat":null,"lon":null,"state":"active","id":null},{"event_id":"scihammer-2025","title":"SciHammer Game Jam 2025","url":"https://itch.io/jam/scihammer-2025","shortener_url":null,"started_at":"2025-02-11T04:00:00.000+09:00","ended_at":"2025-02-17T04:00:00.000+09:00","limit_number":null,"address":null,"place":"Online","lat":null,"lon":null,"state":"active","id":null},{"event_id":"179431","title":"［第3回］Startup Weekend 袋井","url":"https://swfukuroi.doorkeeper.jp/events/179431","shortener_url":null,"started_at":"2025-02-14T18:00:00.000+09:00","ended_at":"2025-02-16T21:00:00.000+09:00","limit_number":60,"address":"〒437-8555 静岡県袋井市豊沢2200-2","place":"静岡理工科大学　土木工学科棟","lat":34.7387,"lon":137.961,"state":"active","id":null},{"event_id":"339348","title":"Open Hack U 2025 NAGOYA","url":"https://hacku.connpass.com/event/339348/","shortener_url":null,"started_at":"2025-02-15T10:00:00.000+09:00","ended_at":"2025-02-15T18:30:00.000+09:00","limit_number":22,"address":"愛知県名古屋市東区葵3-7-14","place":"imy会議室","lat":35.1719,"lon":136.93,"state":"active","id":null},{"event_id":"smoochie-jam-25","title":"Smoochie Jam","url":"https://itch.io/jam/smoochie-jam-25","shortener_url":null,"started_at":"2025-02-01T14:00:00.000+09:00","ended_at":"2025-03-01T16:59:59.000+09:00","limit_number":null,"address":null,"place":"Online","lat":null,"lon":null,"state":"active","id":null},{"event_id":"godot-xr-game-jam-feb-2025","title":"Godot XR Game Jam - Feb 2025","url":"https://itch.io/jam/godot-xr-game-jam-feb-2025","shortener_url":null,"started_at":"2025-02-10T09:00:00.000+09:00","ended_at":"2025-02-17T09:00:00.000+09:00","limit_number":null,"address":null,"place":"Online","lat":null,"lon":null,"state":"active","id":null}]